[
  {
    "processName": "TestData",
    "processId": "1236",
    "state": "Completed",
    "variables": {
      "myInput": {
        "name": "default",
        "age": 10
      },
      "myOutput": {
        "originalInput": {
          "name": "default",
          "age": 10
        },
        "status": true
      },
      "myText": "Sat Apr 29 2023 08:56:53 GMT-0000 (UTC)",
      "counter": 1
    }
  },
  {
    "processName": "TestData",
    "processId": "1236",
    "state": "Completed",
    "variables": {
      "myInput": {
        "name": "default",
        "age": 10
      },
      "myOutput": {
        "originalInput": {
          "name": "default",
          "age": 10
        },
        "status": true
      },
      "myText": "Sat Apr 29 2023 08:56:53 GMT-0000 (UTC)",
      "counter": 1
    }
  },
  {
    "processName": "TestData",
    "processId": "1236",
    "state": "Completed",
    "variables": {
      "myInput": {
        "name": "default",
        "age": 10
      },
      "myOutput": {
        "originalInput": {
          "name": "default",
          "age": 10
        },
        "status": true
      },
      "myText": "Sat Apr 29 2023 08:56:53 GMT-0000 (UTC)",
      "counter": 1
    }
  }
]
